karellen/kombu/__init__.py
karellen/kombu/transport/django/__init__.py
karellen/kombu/transport/django/managers.py
karellen/kombu/transport/django/models.py
karellen/kombu/transport/django/management/__init__.py
karellen/kombu/transport/django/management/commands/__init__.py
karellen/kombu/transport/django/management/commands/clean_kombu_messages.py
karellen/kombu/transport/django/migrations/0001_initial.py
karellen/kombu/transport/django/migrations/__init__.py
karellen/kombu/transport/django/south_migrations/0001_initial.py
karellen/kombu/transport/django/south_migrations/__init__.py
karellen/kombu/transport/sqlalchemy/__init__.py
karellen/kombu/transport/sqlalchemy/models.py
karellen_kombu_ext-4.0.2.dist-info/DESCRIPTION.rst
karellen_kombu_ext-4.0.2.dist-info/METADATA
karellen_kombu_ext-4.0.2.dist-info/RECORD
karellen_kombu_ext-4.0.2.dist-info/WHEEL
karellen_kombu_ext-4.0.2.dist-info/metadata.json
karellen_kombu_ext-4.0.2.dist-info/namespace_packages.txt
karellen_kombu_ext-4.0.2.dist-info/top_level.txt
karellen_kombu_ext-4.0.2.dist-info/zip-safe
