Metadata-Version: 2.0
Name: karellen-kombu-ext
Version: 4.0.2
Summary: Karellen Kombu extensions
Home-page: https://github.com/karellen/karellen-kombu-ext
Author: Karellen, Inc, Arcadiy Ivanov
Author-email: supervisor@karellen.co, arcadiy@karellen.co
License: Apache License, Version 2.0
Platform: UNKNOWN
Classifier: Development Status :: 5 - Production/Stable
Classifier: Environment :: Console
Classifier: Intended Audience :: Developers
Classifier: License :: OSI Approved :: Apache Software License
Classifier: Programming Language :: Python
Classifier: Programming Language :: Python :: 3.5
Classifier: Programming Language :: Python :: 3.3
Classifier: Programming Language :: Python :: 3.4
Classifier: Topic :: Software Development :: Libraries
Classifier: Topic :: Software Development :: Libraries :: Python Modules
Classifier: Topic :: Internet
Requires-Dist: kombu (>=4.0.2)
